setup.py
pinky/__init__.py
pinky/broker/__init__.py
pinky/broker/client.py
pinky/broker/server.py
pinky/broker/service.py
pinky/core/__init__.py
pinky/core/base.py
pinky/core/cache.py
pinky/core/exceptions.py
pinky/core/hash.py
pinky/core/interfaces.py
pinky/core/manhole.py
pinky/core/response.py
pinky/core/serializer/__init__.py
pinky/core/serializer/json_serializer.py
pinky/core/serializer/msgpack_serializer.py
pinky/node/__init__.py
pinky/node/client.py
pinky/node/server.py
pinky/node/service.py
pinky/scripts/__init__.py
pinky/scripts/output.py
pinky/scripts/pinky_broker.py
pinky/scripts/pinky_node.py
pinky/scripts/utils.py
pinky/test/__init__.py
pinky/test/helper.py
pinky/test/test_base.py
pinky/test/test_broker_server.py
pinky/test/test_cache.py
pinky/test/test_exceptions.py
pinky/test/test_interface.py
pinky/test/test_node_server.py
pinky/test/test_output.py
pinky/test/test_response.py
pinky/test/test_serializer.py
txpinky.egg-info/PKG-INFO
txpinky.egg-info/SOURCES.txt
txpinky.egg-info/dependency_links.txt
txpinky.egg-info/entry_points.txt
txpinky.egg-info/not-zip-safe
txpinky.egg-info/requires.txt
txpinky.egg-info/top_level.txt