Metadata-Version: 1.1
Name: txpinky
Version: 0.1.0
Summary: Pinky is a multi node distributed replicated in memory cache application.
Home-page: https://github.com/dr4ke616/pinky
Author: Adam Drakeford
Author-email: adamdrakeford@gmail.com
License: MIT
Platform: UNKNOWN
Classifier: Framework :: Twisted
Classifier: Intended Audience :: Developers
Classifier: Operating System :: POSIX :: Linux
Classifier: Programming Language :: Python
Classifier: Programming Language :: Python :: 2.7
Classifier: Programming Language :: Python :: Implementation :: CPython
Classifier: Topic :: Software Development
Classifier: Topic :: System :: Networking
Classifier: Topic :: Software Development :: Libraries
Classifier: Topic :: Software Development :: Libraries :: Python Modules
